{
	"name": "Customers - 8-11-14-18-20",
	"properties": {
		"annotations": [],
		"runtimeState": "Started",
		"pipelines": [
			{
				"pipelineReference": {
					"referenceName": "Copy Data SQL",
					"type": "PipelineReference"
				},
				"parameters": {
					"TriggerGroup": "Customer"
				}
			}
		],
		"type": "ScheduleTrigger",
		"typeProperties": {
			"recurrence": {
				"frequency": "Day",
				"interval": 1,
				"startTime": "2020-02-18T15:31:00.000Z",
				"timeZone": "UTC",
				"schedule": {
					"minutes": [
						0
					],
					"hours": [
						1,
						4,
						7,
						11,
						13
					]
				}
			}
		}
	}
}