{
	"$schema": "http://schema.management.azure.com/schemas/2015-01-01/deploymentTemplate.json#",
	"contentVersion": "1.0.0.0",
	"parameters": {
		"factoryName": {
			"type": "string",
			"metadata": "Data Factory Name",
			"defaultValue": "ccaidauesadf001"
		}
	},
	"variables": {
		"factoryId": "[concat('Microsoft.DataFactory/factories/', parameters('factoryName'))]"
	},
	"resources": [
		{
			"name": "[concat(parameters('factoryName'), '/SendToBI')]",
			"type": "Microsoft.DataFactory/factories/pipelines",
			"apiVersion": "2018-06-01",
			"properties": {
				"activities": [
					{
						"name": "Copy Send To BI",
						"type": "Copy",
						"dependsOn": [],
						"policy": {
							"timeout": "7.00:00:00",
							"retry": 0,
							"retryIntervalInSeconds": 30,
							"secureOutput": false,
							"secureInput": false
						},
						"userProperties": [],
						"typeProperties": {
							"source": {
								"type": "AzureSqlSource",
								"sqlReaderQuery": "SELECT \n'ND' as UPDATE_STATUS,\nSubstring(Mainkey, 1, 6) as MAINKEY,\nSubstring(Subkey, 1, 7) as SUBKEY,\nSubstring([Data], 1, 80) as DATAFIELD\nFrom [Configuration]\nwhere [Mainkey] = 'SendToBI'\nAnd substring ([param], 1, 1) = '1'\nAnd [Application]='BACKEND'"
							},
							"sink": {
								"type": "AzureSqlSink",
								"preCopyScript": "truncate table CoreConfigurationToBI"
							},
							"enableStaging": false,
							"enableSkipIncompatibleRow": false,
							"translator": {
								"type": "TabularTranslator",
								"mappings": [
									{
										"source": {
											"name": "UPDATE_STATUS",
											"type": "String"
										},
										"sink": {
											"name": "UPDATE_STATUS",
											"type": "String"
										}
									},
									{
										"source": {
											"name": "MAINKEY",
											"type": "String"
										},
										"sink": {
											"name": "MAINKEY",
											"type": "String"
										}
									},
									{
										"source": {
											"name": "SUBKEY",
											"type": "String"
										},
										"sink": {
											"name": "SUBKEY",
											"type": "String"
										}
									},
									{
										"source": {
											"name": "DATAFIELD",
											"type": "String"
										},
										"sink": {
											"name": "DATAFIELD",
											"type": "String"
										}
									}
								]
							}
						},
						"inputs": [
							{
								"referenceName": "DEV_CORE_Configuration",
								"type": "DatasetReference"
							}
						],
						"outputs": [
							{
								"referenceName": "DEV_CORE_CoreConfigurationToBI",
								"type": "DatasetReference"
							}
						]
					}
				],
				"annotations": []
			},
			"dependsOn": [
				"[concat(variables('factoryId'), '/datasets/DEV_CORE_CoreConfigurationToBI')]"
			]
		},
		{
			"name": "[concat(parameters('factoryName'), '/DEV_CORE_CoreConfigurationToBI')]",
			"type": "Microsoft.DataFactory/factories/datasets",
			"apiVersion": "2018-06-01",
			"properties": {
				"linkedServiceName": {
					"referenceName": "IR2_CORE_DEV",
					"type": "LinkedServiceReference"
				},
				"folder": {
					"name": "Development"
				},
				"annotations": [],
				"type": "AzureSqlTable",
				"schema": [
					{
						"name": "UPDATE_STATUS",
						"type": "varchar"
					},
					{
						"name": "MAINKEY",
						"type": "varchar"
					},
					{
						"name": "SUBKEY",
						"type": "varchar"
					},
					{
						"name": "DATAFIELD",
						"type": "varchar"
					},
					{
						"name": "CreateDate",
						"type": "datetimeoffset",
						"scale": 7
					},
					{
						"name": "ModifiedDate",
						"type": "datetimeoffset",
						"scale": 7
					}
				],
				"typeProperties": {
					"tableName": "[[dbo].[CoreConfigurationToBI]"
				}
			},
			"dependsOn": []
		}
	]
}